mcpccc/__init__.py
mcpccc-0.2.3.dist-info/WHEEL
mcpccc-0.2.3.dist-info/entry_points.txt
mcpccc-0.2.3.dist-info/METADATA
mcpccc-0.2.3.dist-info/RECORD
