Metadata-Version: 2.3
Name: mcpccc
Version: 0.2.3
Summary: Add your description here
Author: liujingjing
Author-email: liujingjing <>
Requires-Dist: mcp[cli]>=1.12.3
Requires-Dist: requests>=2.31.0
Requires-Python: >=3.12
